<?xml version="1.0" encoding="UTF-8" standalone="yes"?>
<AssignMessage async="false" continueOnError="false" enabled="true" name="AM-SetInvalidTransactionTypeError">
    <DisplayName>AM-SetInvalidTransactionTypeError</DisplayName>
    <Properties/>
    <Set>
        <Payload content-type="application/xml">
            <XML>
                <Response>Invalid Transaction Type</Response>
                <MessageType>1210</MessageType>
                <NotificationId>{notificationid}</NotificationId>
                <ActCode>102</ActCode>
                <ProcCode>{proccode}</ProcCode>
            </XML>
        </Payload>
        <Headers>
            <Header name="Content-Type">application/xml</Header>
        </Headers>
        <StatusCode>200</StatusCode>
        <ReasonPhrase>OK</ReasonPhrase>
    </Set>
    <AssignVariable>
        <Name>flowType</Name>
        <Value>ERROR_HANDLING_FLOW</Value>
    </AssignVariable>
    <IgnoreUnresolvedVariables>true</IgnoreUnresolvedVariables>
    <AssignTo createNew="false" transport="http" type="response"/>
</AssignMessage>